[
{
    "name":"oil-gas",
    "text": "OIL & GAS",
    "background": "blue",
    "imports":[
        "corrosion-inhibitor",
        "descalant",
        "acidizer",
        "acidulant",
        "metal-ion-control"
    ]
},
{
    "name":"industrial-institutional-cleaners",
    "text": "INDUSTRIAL & INSTITUTIONAL CLEANERS",
    "background": "blue",
    "imports":[
        "detergent-builder",
        "anti-redeposition",
        "descalant",
        "metal-ion-control"
    ]
},
{
    "name":"concrete-additives",
    "text": "CONCRETE ADDITIVES",
    "background": "blue",
    "imports":[
        "corrosion-inhibitor",
        "plasticizer",
        "set-retarder",
        "descalant",
        "metal-ion-control"
    ]
},
{
    "name":"road-safety",
    "text": "ROAD SAFETY",
    "background": "blue",
    "imports":[
        "corrosion-inhibitor"
    ]
},
{
    "name":"water",
    "text": "WATER",
    "background": "blue",
    "imports":[
        "descalant",
        "metal-ion-control"
    ]
},
{
    "name":"agriculture",
    "text": "AGRICULTURE",
    "background": "blue",
    "imports":[
        "controlled-delivery",
        "metal-ion-control"
    ]
},
{
    "name":"pulp-paper",
    "text": "PULP & PAPER",
    "background": "blue",
    "imports":[
        "descalant"
    ]
},
{
    "name":"personal-care",
    "text": "PERSONAL CARE",
    "background": "blue",
    "imports":[
        "antioxidant"
    ]
},
{
    "name":"pharmaceutical",
    "text": "PHARMA-CEUTICAL",
    "background": "blue",
    "imports":[
        "controlled-delivery"
    ]
},
{
    "name":"food-nutrition",
    "text": "FOOD & NUTRITION",
    "background": "blue",
    "imports":[
        "antioxidant",
        "acidulant",
        "metal-ion-control"
    ]
},
{
    "name":"fabric-homecare",
    "text": "FABRIC & HOMECARE",
    "background": "blue",
    "imports":[
        "corrosion-inhibitor",
        "detergent-builder",
        "anti-redeposition",
        "agent-structurant",
        "descalant"
    ]
},


{
    "name":"metal-ion-control",
    "text": "METAL ION CONTROL",
    "background": "grey",
    "imports":[
        "fabric-homecare",
        "food-nutrition",
        "agriculture",
        "concrete-additives",
        "water",
        "industrial-institutional-cleaners",
        "oil-gas"
    ],
    "functionality":[
        "preservation",
        "dispertion",
        "chelation"
    ]
},
{
    "name":"acidulant",
    "text": "ACIDULANT",
    "background": "grey",
    "imports":[
        "food-nutrition",
        "oil-gas"
    ],
    "functionality":[
        "flavor-modification",
        "ph-modification"
    ]
},
{
    "name":"acidizer",
    "text": "ACIDIZER",
    "background": "grey",
    "imports":[
        "oil-gas"
    ],
    "functionality":[
        "ph-modification",
        "chelation"
    ]
},
{
    "name":"descalant",
    "text": "DESCALANT ANIT-SCALANT",
    "background": "grey",
    "imports":[
        "fabric-homecare",
        "pulp-paper",
        "water",
        "industrial-institutional-cleaners",
        "oil-gas"
    ],
    "functionality":[
        "dispertion",
        "ph-modification",
        "chelation"
    ]
},
{
    "name":"agent-structurant",
    "text": "AGENT STRUCTURANT",
    "background": "grey",
    "imports":[
        "fabric-homecare"
    ],
    "functionality":[
        "absorption",
        "adhesion",
        "dispertion"
    ]
},
{
    "name":"anti-redeposition",
    "text": "ANTI- REDEPOSITION",
    "background": "grey",
    "imports":[
        "fabric-homecare",
        "industrial-institutional-cleaners"
    ],
    "functionality":[
        "absorption",
        "dispertion"
    ]
},
{
    "name":"antioxidant",
    "text": "ANTIOXIDANT",
    "background": "grey",
    "imports":[
        "food-nutrition",
        "personal-care"
    ],
    "functionality":[
        "preservation"
    ]
},
{
    "name":"controlled-delivery",
    "text": "CONTROLLED DELIVERY",
    "background": "grey",
    "imports":[
        "agriculture",
        "pharmaceutical"
    ],
    "functionality":[
        "permeation",
        "barrier"
    ]
},
{
    "name":"set-retarder",
    "text": "SET RETARDER",
    "background": "grey",
    "imports":[
        "concrete-additives"
    ],
    "functionality":[
        "chelation"
    ]
},
{
    "name":"plasticizer",
    "text": "PLASTICIZER",
    "background": "grey",
    "imports":[
        "concrete-additives"
    ],
    "functionality":[
        "dispertion"
    ]
},
{
    "name":"detergent-builder",
    "text": "DETERGENT BUILDER",
    "background": "grey",
    "imports":[
        "industrial-institutional-cleaners",
        "fabric-homecare"
    ],
    "functionality":[
        "dispertion",
        "ph-modification",
        "chelation"
    ]
},
{
    "name":"corrosion-inhibitor",
    "text": "CORROSIOIN INHIBITOR",
    "background": "grey",
    "imports":[
        "oil-gas",
        "concrete-additives",
        "road-safety",
        "fabric-homecare"
    ],
    "functionality":[
        "barrier",
        "preservation",
        "absorption",
        "chelation"
    ]
}
]